craft_cli/__init__.py
craft_cli/_version.py
craft_cli/dispatcher.py
craft_cli/errors.py
craft_cli/helptexts.py
craft_cli/messages.py
craft_cli/printer.py
craft_cli/py.typed
craft_cli/pytest_plugin.py
craft_cli/utils.py
craft_cli/completion/__init__.py
craft_cli/completion/__main__.py
craft_cli/completion/bash_completion.sh.j2
craft_cli/completion/completion.py
craft_cli-3.2.0.dist-info/LICENSE
craft_cli-3.2.0.dist-info/METADATA
craft_cli-3.2.0.dist-info/WHEEL
craft_cli-3.2.0.dist-info/entry_points.txt
craft_cli-3.2.0.dist-info/top_level.txt
craft_cli-3.2.0.dist-info/RECORD
