Metadata-Version: 2.1
Name: craft-cli
Version: 3.2.0
Summary: Command Line Interface
Author-email: Canonical Ltd <snapcraft@lists.snapcraft.io>
License: GNU LESSER GENERAL PUBLIC LICENSE
Project-URL: Website, https://github.com/canonical/craft-cli
Project-URL: Documentation, https://craft-cli.readthedocs.io/en/latest/
Project-URL: Source, https://github.com/canonical/craft-cli.git
Project-URL: Issues, https://github.com/canonical/craft-cli/issues
Classifier: Development Status :: 5 - Production/Stable
Classifier: Framework :: Pytest
Classifier: Intended Audience :: Developers
Classifier: Operating System :: MacOS :: MacOS X
Classifier: Operating System :: Microsoft :: Windows
Classifier: Operating System :: POSIX :: Linux
Classifier: Programming Language :: Python :: 3
Classifier: Programming Language :: Python :: 3.10
Classifier: Programming Language :: Python :: 3.11
Classifier: Programming Language :: Python :: 3.12
Requires-Python: >=3.10
License-File: LICENSE
Requires-Dist: platformdirs
Requires-Dist: jinja2 >=3.1.5
Requires-Dist: overrides >=7.7.0
Requires-Dist: typing-extensions
Requires-Dist: pywin32 ; sys_platform == "win32"
